fastberry/__init__.py
fastberry/app.py
fastberry/components.py
fastberry/core/__init__.py
fastberry/core/types.py
fastberry/extras/__init__.py
fastberry/extras/authcookie.py
fastberry/extras/redirect_root.py
fastberry/framework.py
fastberry/graphql/__init__.py
fastberry/graphql/edges.py
fastberry/graphql/types.py
fastberry/handlers/__init__.py
fastberry/handlers/api_info.py
fastberry/handlers/cmd/__init__.py
fastberry/handlers/cmd/action/__init__.py
fastberry/handlers/cmd/action/plugin_maker.py
fastberry/handlers/cmd/gql/__init__.py
fastberry/handlers/cmd/gql/client.py
fastberry/handlers/cmd/gql/js_utils/pySchema.js
fastberry/handlers/cmd/gql/js_utils/readme.md
fastberry/handlers/cmd/gql/reader.py
fastberry/handlers/cmd/gql/utils.py
fastberry/handlers/cmd/graphql.py
fastberry/handlers/cmd/run.py
fastberry/handlers/cmd/shell.py
fastberry/handlers/cmd/sql_alembic.py
fastberry/handlers/cmd/start_app.py
fastberry/handlers/cmd/templates/base_app/__init__.py
fastberry/handlers/cmd/templates/base_app/forms.py
fastberry/handlers/cmd/templates/base_app/graphql/__init__.py
fastberry/handlers/cmd/templates/base_app/graphql/demo.py
fastberry/handlers/cmd/templates/base_app/manager.py
fastberry/handlers/cmd/templates/base_app/types.py
fastberry/handlers/cmd/templates/base_app.zip
fastberry/handlers/cmd/templates/zeus-graphql/app.ts
fastberry/handlers/cmd/templates/zeus-graphql/package.json
fastberry/handlers/cmd/templates/zeus-graphql/README.md
fastberry/handlers/cmd/templates/zeus-graphql.zip
fastberry/handlers/commands.py
fastberry/handlers/extras.py
fastberry/handlers/forms.py
fastberry/handlers/graphql/__init__.py
fastberry/handlers/graphql/base.py
fastberry/handlers/graphql/schema.py
fastberry/handlers/pagination.py
fastberry/handlers/routers.py
fastberry/handlers/types.py
fastberry/scripts/__init__.py
fastberry/scripts/shell.py
fastberry/scripts/start_project.py
fastberry/scripts/templates/project-template/.gitignore
fastberry-0.0.80.dist-info/entry_points.txt
fastberry-0.0.80.dist-info/WHEEL
fastberry-0.0.80.dist-info/METADATA
fastberry-0.0.80.dist-info/licenses/LICENSE
fastberry-0.0.80.dist-info/RECORD
