Metadata-Version: 2.1
Name: fastberry
Version: 0.0.80
Summary: GraphQL Made Easy
Author-email: hlop3z <23062270+hlop3z@users.noreply.github.com>
Requires-Python: >=3.10
Classifier: Intended Audience :: Developers
Classifier: License :: OSI Approved :: MIT License
Classifier: Programming Language :: Python :: 3
Classifier: Programming Language :: Python :: 3.10
Requires-Dist: click>=8.1.3
Requires-Dist: fastapi>=0.88.0
Requires-Dist: spoc>=0.1.5
Requires-Dist: strawberry-graphql>=0.146.0
Requires-Dist: uvicorn[standard]>=0.18.3
Provides-Extra: mongo
Requires-Dist: dbcontroller[mongo]>=0.1.52; extra == "mongo"
Provides-Extra: sql
Requires-Dist: dbcontroller[sql]>=0.1.52; extra == "sql"
Provides-Extra: testing
Requires-Dist: dbcontroller[testing]>=0.1.52; extra == "testing"
Project-URL: Documentation, https://hlop3z.github.io/fastberry/
Project-URL: Homepage, https://github.com/hlop3z/fastberry/
